MANIFEST.in
README.txt
requirements.txt
setup.py
lamvery/__init__.py
lamvery/build.py
lamvery/cli.py
lamvery/config.py
lamvery/env.py
lamvery/log.py
lamvery/secret.py
lamvery/utils.py
lamvery.egg-info/PKG-INFO
lamvery.egg-info/SOURCES.txt
lamvery.egg-info/dependency_links.txt
lamvery.egg-info/entry_points.txt
lamvery.egg-info/requires.txt
lamvery.egg-info/top_level.txt
lamvery/actions/__init__.py
lamvery/actions/api.py
lamvery/actions/base.py
lamvery/actions/build.py
lamvery/actions/configure.py
lamvery/actions/decrypt.py
lamvery/actions/deploy.py
lamvery/actions/encrypt.py
lamvery/actions/encrypt_file.py
lamvery/actions/events.py
lamvery/actions/generate.py
lamvery/actions/init.py
lamvery/actions/invoke.py
lamvery/actions/logs.py
lamvery/actions/rollback.py
lamvery/actions/set_alias.py
lamvery/clients/__init__.py
lamvery/clients/apigateway.py
lamvery/clients/base.py
lamvery/clients/events.py
lamvery/clients/function.py
lamvery/clients/kms.py
lamvery/clients/logs.py
lamvery/dists/lamvery.js