Metadata-Version: 1.1
Name: lamvery
Version: 0.17.3
Summary: User-friendly deploy and management tool for AWS Lambda function.
Home-page: https://github.com/marcy-terui/lamvery
Author: Masashi Terui
Author-email: marcy9114+pypi@gmail.com
License: MIT License
Keywords: aws lambda
Platform: UNKNOWN
Classifier: Development Status :: 4 - Beta
Classifier: Intended Audience :: Developers
Classifier: Intended Audience :: System Administrators
Classifier: License :: OSI Approved :: MIT License
Classifier: Programming Language :: Python
Classifier: Programming Language :: Python :: 2.7
